{"title":"Combined feed","url":"https://ITCORD.github.io/legacy/all.xml","elements":[{"title":"레드매직, VC 쿨러 5 프로 스마트폰용 쿨러 출시 (펀샵 ─ 펀테나 ─ 최신)","contents":"<a name=\"category\" data-categoryno=\"2\" style=\"cursor: pointer\">PC/모바일</a>","link":"https://www.funshop.co.kr/Story/FuntennaView/21068#","retrieved":1712188800000,"image":"https://cdn.funshop.co.kr/www/renew/common/d280x280.jpg"},{"title":"샤오미, 67W 데스크톱 고속 충전 도킹 스테이션 프로 출시 (펀샵 ─ 펀테나 ─ 최신)","contents":"<a name=\"category\" data-categoryno=\"2\" style=\"cursor: pointer\">PC/모바일</a>","link":"https://www.funshop.co.kr/Story/FuntennaView/21067#","retrieved":1712188800000,"image":"https://cdn.funshop.co.kr/www/renew/common/d280x280.jpg"},{"title":"트래비스 스콧 x 조던, 점프맨 잭 출시 예정 (펀샵 ─ 펀테나 ─ 최신)","contents":"<a name=\"category\" data-categoryno=\"7\" style=\"cursor: pointer\">패션/시계/가방</a>","link":"https://www.funshop.co.kr/Story/FuntennaView/21066#","retrieved":1712188800000,"image":"https://cdn.funshop.co.kr/www/renew/common/d280x280.jpg"},{"title":"에이수스, ROG Keris II Ace 게이밍 마우스 공개 (펀샵 ─ 펀테나 ─ 최신)","contents":"<a name=\"category\" data-categoryno=\"2\" style=\"cursor: pointer\">PC/모바일</a>","link":"https://www.funshop.co.kr/Story/FuntennaView/21065#","retrieved":1712102400000,"image":"https://cdn.funshop.co.kr/www/renew/common/d280x280.jpg"},{"title":"JLab, Studio Pro ANC 무선 오버이어 헤드폰 공개 (펀샵 ─ 펀테나 ─ 최신)","contents":"<a name=\"category\" data-categoryno=\"8\" style=\"cursor: pointer\">취미/기타</a>","link":"https://www.funshop.co.kr/Story/FuntennaView/21064#","retrieved":1712102400000,"image":"https://cdn.funshop.co.kr/www/renew/common/d280x280.jpg"},{"title":"삼성전자, 피트니스 밴드 갤럭시 핏3 출시 (펀샵 ─ 펀테나 ─ 최신)","contents":"<a name=\"category\" data-categoryno=\"2\" style=\"cursor: pointer\">PC/모바일</a>","link":"https://www.funshop.co.kr/Story/FuntennaView/21063#","retrieved":1712102400000,"image":"https://cdn.funshop.co.kr/www/renew/common/d280x280.jpg"},{"title":"[해외펀딩] 계단을 오르는 로봇 청소기 MIGO Ascender. (펀샵 ─ 펀테나 ─ 최신)","contents":"<a name=\"category\" data-categoryno=\"6\" style=\"cursor: pointer\">미래기술</a>","link":"https://www.funshop.co.kr/Story/FuntennaView/21059#","retrieved":1712016000000,"image":"https://cdn.funshop.co.kr/www/renew/common/d280x280.jpg"},{"title":"레이저, 만우절 기념 게이밍 체어 크툴루 공개 (펀샵 ─ 펀테나 ─ 최신)","contents":"<a name=\"category\" data-categoryno=\"5\" style=\"cursor: pointer\">트렌드</a>","link":"https://www.funshop.co.kr/Story/FuntennaView/21062#","retrieved":1712016000000,"image":"https://cdn.funshop.co.kr/www/renew/common/d280x280.jpg"}]}