{"title":"Combined feed","url":"https://ITCORD.github.io/legacy/all.xml","elements":[{"title":"퓨리오사, 매드 맥스 사가 공식 예고편 공개 (펀샵 ─ 펀테나 ─ 최신)","contents":"<a name=\"category\" data-categoryno=\"5\" style=\"cursor: pointer\">트렌드</a>","link":"https://www.funshop.co.kr/Story/FuntennaView/20784#","retrieved":1701734400000,"image":"https://cdn.funshop.co.kr/www/renew/common/d280x280.jpg"},{"title":"나이키 ACG, 토레 미드 워터프루프 출시 (펀샵 ─ 펀테나 ─ 최신)","contents":"<a name=\"category\" data-categoryno=\"7\" style=\"cursor: pointer\">패션/시계/가방</a>","link":"https://www.funshop.co.kr/Story/FuntennaView/20782#","retrieved":1701734400000,"image":"https://cdn.funshop.co.kr/www/renew/common/d280x280.jpg"},{"title":"8Bitdo, 얼티밋 컨트롤러 원신 중운 에디션 출시 (펀샵 ─ 펀테나 ─ 최신)","contents":"<a name=\"category\" data-categoryno=\"8\" style=\"cursor: pointer\">취미/기타</a>","link":"https://www.funshop.co.kr/Story/FuntennaView/20781#","retrieved":1701734400000,"image":"https://cdn.funshop.co.kr/www/renew/common/d280x280.jpg"},{"title":"캐논데일, 테소로 네오 카본 전기자전거 출시 (펀샵 ─ 펀테나 ─ 최신)","contents":"<a name=\"category\" data-categoryno=\"4\" style=\"cursor: pointer\">아웃도어/스포츠</a>","link":"https://www.funshop.co.kr/Story/FuntennaView/20780#","retrieved":1701648000000,"image":"https://cdn.funshop.co.kr/www/renew/common/d280x280.jpg"},{"title":"터틀 비치, 스텔스 울트라 게임 컨트롤러 출시 (펀샵 ─ 펀테나 ─ 최신)","contents":"<a name=\"category\" data-categoryno=\"8\" style=\"cursor: pointer\">취미/기타</a>","link":"https://www.funshop.co.kr/Story/FuntennaView/20779#","retrieved":1701648000000,"image":"https://cdn.funshop.co.kr/www/renew/common/d280x280.jpg"},{"title":"나이키, 에어 폼포짓 원 '에그 플랜트' 출시 예정 (펀샵 ─ 펀테나 ─ 최신)","contents":"<a name=\"category\" data-categoryno=\"7\" style=\"cursor: pointer\">패션/시계/가방</a>","link":"https://www.funshop.co.kr/Story/FuntennaView/20778#","retrieved":1701648000000,"image":"https://cdn.funshop.co.kr/www/renew/common/d280x280.jpg"},{"title":"[해외펀딩] 크리에이터를 위한 화면 달린 키보드, Monogram Keyboard. (펀샵 ─ 펀테나 ─ 최신)","contents":"<a name=\"category\" data-categoryno=\"2\" style=\"cursor: pointer\">PC/모바일</a>","link":"https://www.funshop.co.kr/Story/FuntennaView/20777#","retrieved":1701388800000,"image":"https://cdn.funshop.co.kr/abroad/041/20777/thumbnail_1.jpg"},{"title":"클레이모어 휴대용 블루투스 스피커 (펀샵 ─ 펀테나 ─ 최신)","contents":"<a name=\"category\" data-categoryno=\"8\" style=\"cursor: pointer\">취미/기타</a>","link":"https://www.funshop.co.kr/Story/FuntennaView/20774#","retrieved":1701388800000,"image":"https://cdn.funshop.co.kr/abroad/041/20774/thumbnail_1.jpg"}]}