{"title":"Combined feed","url":"https://ITCORD.github.io/legacy/all.xml","elements":[{"title":"NZXT, 릴레이 오디오 생태계 출시 (펀샵 ─ 펀테나 ─ 최신)","contents":"<a name=\"category\" data-categoryno=\"2\" style=\"cursor: pointer\">PC/모바일</a>","link":"https://www.funshop.co.kr/Story/FuntennaView/20410#","retrieved":1688688000000,"image":"https://cdn.funshop.co.kr/abroad/040/20410/thumbnail_1.jpg"},{"title":"JSAUX, 스팀덱용 투명 전면 커버 시리즈 출시 (펀샵 ─ 펀테나 ─ 최신)","contents":"<a name=\"category\" data-categoryno=\"8\" style=\"cursor: pointer\">취미/기타</a>","link":"https://www.funshop.co.kr/Story/FuntennaView/20409#","retrieved":1688688000000,"image":"https://cdn.funshop.co.kr/www/renew/common/d280x280.jpg"},{"title":"몽블랑, MTB 03 ANC 이어버드 출시 (펀샵 ─ 펀테나 ─ 최신)","contents":"<a name=\"category\" data-categoryno=\"8\" style=\"cursor: pointer\">취미/기타</a>","link":"https://www.funshop.co.kr/Story/FuntennaView/20408#","retrieved":1688688000000,"image":"https://cdn.funshop.co.kr/www/renew/common/d280x280.jpg"},{"title":"[해외펀딩] 멀티 터치패드 CheerTok. (펀샵 ─ 펀테나 ─ 최신)","contents":"<a name=\"category\" data-categoryno=\"2\" style=\"cursor: pointer\">PC/모바일</a>","link":"https://www.funshop.co.kr/Story/FuntennaView/20411#","retrieved":1688601600000,"image":"https://cdn.funshop.co.kr/abroad/040/20411/thumbnail_1.jpg"},{"title":"BMW, Exploro 자전거 라인업 공개 (펀샵 ─ 펀테나 ─ 최신)","contents":"<a name=\"category\" data-categoryno=\"4\" style=\"cursor: pointer\">아웃도어/스포츠</a>","link":"https://www.funshop.co.kr/Story/FuntennaView/20407#","retrieved":1688601600000,"image":"https://cdn.funshop.co.kr/abroad/040/20407/thumbnail_1.jpg"},{"title":"레고, Liebherr LR 13000 크롤러 크레인 출시예정 (펀샵 ─ 펀테나 ─ 최신)","contents":"<a name=\"category\" data-categoryno=\"8\" style=\"cursor: pointer\">취미/기타</a>","link":"https://www.funshop.co.kr/Story/FuntennaView/20406#","retrieved":1688601600000,"image":"https://cdn.funshop.co.kr/www/renew/common/d280x280.jpg"},{"title":"Boox, 컬러 ePaper 태블릿 Tab Mini C 출시 (펀샵 ─ 펀테나 ─ 최신)","contents":"<a name=\"category\" data-categoryno=\"8\" style=\"cursor: pointer\">취미/기타</a>","link":"https://www.funshop.co.kr/Story/FuntennaView/20405#","retrieved":1688601600000,"image":"https://cdn.funshop.co.kr/abroad/040/20405/thumbnail_1.jpg"},{"title":"[해외펀딩] 모듈식 충전 거치대 Matrix (펀샵 ─ 펀테나 ─ 최신)","contents":"<a name=\"category\" data-categoryno=\"2\" style=\"cursor: pointer\">PC/모바일</a>","link":"https://www.funshop.co.kr/Story/FuntennaView/20404#","retrieved":1688515200000,"image":"https://cdn.funshop.co.kr/abroad/040/20404/thumbnail_1.jpg"}]}