{"title":"Combined feed","url":"https://ITCORD.github.io/legacy/all.xml","elements":[{"title":"에이수스, ROG CETRA TRUE WIRELESS PRO 공개 (펀샵 ─ 펀테나 ─ 최신)","contents":"<a name=\"category\" data-categoryno=\"8\" style=\"cursor: pointer\">취미/기타</a>","link":"https://www.funshop.co.kr/Story/FuntennaView/19522#","retrieved":1658275200000,"image":"https://cdn.funshop.co.kr/abroad/039/19522/thumbnail_1.jpg"},{"title":"오데마 피게, 로열 오크 오프쇼어 뮤직 에디션 출시 (펀샵 ─ 펀테나 ─ 최신)","contents":"<a name=\"category\" data-categoryno=\"7\" style=\"cursor: pointer\">패션/시계/가방</a>","link":"https://www.funshop.co.kr/Story/FuntennaView/19521#","retrieved":1658275200000,"image":"https://cdn.funshop.co.kr/abroad/039/19521/thumbnail_1.jpg"},{"title":"Levante, 완전방수 모듈러 확장 백팩 (펀샵 ─ 펀테나 ─ 최신)","contents":"<a name=\"category\" data-categoryno=\"7\" style=\"cursor: pointer\">패션/시계/가방</a>","link":"https://www.funshop.co.kr/Story/FuntennaView/19520#","retrieved":1658275200000,"image":"https://cdn.funshop.co.kr/abroad/039/19520/thumbnail_1.jpg"},{"title":"노키아, 피처폰 5710 XpressAudio 출시 (펀샵 ─ 펀테나 ─ 최신)","contents":"<a name=\"category\" data-categoryno=\"2\" style=\"cursor: pointer\">PC/모바일</a>","link":"https://www.funshop.co.kr/Story/FuntennaView/19519#","retrieved":1658275200000,"image":"https://cdn.funshop.co.kr/abroad/039/19519/thumbnail_1.jpg"},{"title":"포커스라이트, Vocaster 시리즈 출시 예정 (펀샵 ─ 펀테나 ─ 최신)","contents":"<a name=\"category\" data-categoryno=\"8\" style=\"cursor: pointer\">취미/기타</a>","link":"https://www.funshop.co.kr/Story/FuntennaView/19518#","retrieved":1658188800000,"image":"https://cdn.funshop.co.kr/abroad/039/19518/thumbnail_1.jpg"},{"title":"Kingston, DataTraveler Max A타입 출시 (펀샵 ─ 펀테나 ─ 최신)","contents":"<a name=\"category\" data-categoryno=\"2\" style=\"cursor: pointer\">PC/모바일</a>","link":"https://www.funshop.co.kr/Story/FuntennaView/19517#","retrieved":1658188800000,"image":"https://cdn.funshop.co.kr/abroad/039/19517/thumbnail_1.jpg"},{"title":"Huntkey, 서지보호 100W GaN 충전기 출시 (펀샵 ─ 펀테나 ─ 최신)","contents":"<a name=\"category\" data-categoryno=\"2\" style=\"cursor: pointer\">PC/모바일</a>","link":"https://www.funshop.co.kr/Story/FuntennaView/19516#","retrieved":1658188800000,"image":"https://cdn.funshop.co.kr/abroad/039/19516/thumbnail_1.jpg"},{"title":"예티, 로디 48 휠 쿨러 (펀샵 ─ 펀테나 ─ 최신)","contents":"<a name=\"category\" data-categoryno=\"4\" style=\"cursor: pointer\">아웃도어/스포츠</a>","link":"https://www.funshop.co.kr/Story/FuntennaView/19514#","retrieved":1658188800000,"image":"https://cdn.funshop.co.kr/abroad/039/19514/thumbnail_1.jpg"}]}