{"title":"펀샵 ─ 펀테나 ─ 최신","url":"https://www.funshop.co.kr/Story/FuntennaList","favicon":"https://www.funshop.co.kr/Story/favicon.ico","elements":[{"title":"[해외펀딩] 놀랍고도 아름다운 키네틱 아트 Oasis Mini.","contents":"<a name=\"category\" data-categoryno=\"8\" style=\"cursor: pointer\">취미/기타</a>","link":"https://www.funshop.co.kr/Story/FuntennaView/20452#","retrieved":1689897600000,"image":"https://cdn.funshop.co.kr/www/renew/common/d280x280.jpg"},{"title":"애플, 비츠 스튜디오 프로 출시","contents":"<a name=\"category\" data-categoryno=\"8\" style=\"cursor: pointer\">취미/기타</a>","link":"https://www.funshop.co.kr/Story/FuntennaView/20451#","retrieved":1689897600000,"image":"https://cdn.funshop.co.kr/abroad/040/20451/thumbnail_1.jpg"},{"title":"Plugable, USB4 도킹 스테이션 UD-4VPD 출시","contents":"<a name=\"category\" data-categoryno=\"2\" style=\"cursor: pointer\">PC/모바일</a>","link":"https://www.funshop.co.kr/Story/FuntennaView/20450#","retrieved":1689897600000,"image":"https://cdn.funshop.co.kr/abroad/040/20450/thumbnail_1.jpg"},{"title":"소더비스, 오메가 스포츠 애플 컴퓨터 스니커즈 공개","contents":"<a name=\"category\" data-categoryno=\"8\" style=\"cursor: pointer\">취미/기타</a>","link":"https://www.funshop.co.kr/Story/FuntennaView/20449#","retrieved":1689897600000,"image":"https://cdn.funshop.co.kr/abroad/040/20449/thumbnail_1.jpg"},{"title":"[해외펀딩] 그림을 그리면 벡터 이미지로, Shaper Trace.","contents":"<a name=\"category\" data-categoryno=\"8\" style=\"cursor: pointer\">취미/기타</a>","link":"https://www.funshop.co.kr/Story/FuntennaView/20448#","retrieved":1689811200000,"image":"https://cdn.funshop.co.kr/abroad/040/20448/thumbnail_1.jpg"},{"title":"커세어, NIGHTSABRE WIRELESS 게이밍 마우스","contents":"<a name=\"category\" data-categoryno=\"2\" style=\"cursor: pointer\">PC/모바일</a>","link":"https://www.funshop.co.kr/Story/FuntennaView/20446#","retrieved":1689811200000,"image":"https://cdn.funshop.co.kr/abroad/040/20446/thumbnail_1.jpg"},{"title":"레고, 월트 디즈니 헌정 카메라 출시예정","contents":"<a name=\"category\" data-categoryno=\"8\" style=\"cursor: pointer\">취미/기타</a>","link":"https://www.funshop.co.kr/Story/FuntennaView/20444#","retrieved":1689811200000,"image":"https://cdn.funshop.co.kr/www/renew/common/d280x280.jpg"},{"title":"벤츠, GLC43 AMG 공개","contents":"<a name=\"category\" data-categoryno=\"1\" style=\"cursor: pointer\">자동차/모터사이클</a>","link":"https://www.funshop.co.kr/Story/FuntennaView/20447#","retrieved":1689724800000,"image":"https://cdn.funshop.co.kr/abroad/040/20447/thumbnail_1.jpg"}]}