{"title":"펀샵 ─ 펀테나 ─ 최신","url":"https://www.funshop.co.kr/Story/FuntennaList","favicon":"https://www.funshop.co.kr/Story/favicon.ico","elements":[{"title":"km5, 오픈에어타입 헤드폰 HP1 출시","contents":"<a name=\"category\" data-categoryno=\"8\" style=\"cursor: pointer\">취미/기타</a>","link":"https://www.funshop.co.kr/Story/FuntennaView/21329#","retrieved":1721952000000,"image":"https://cdn.funshop.co.kr/www/renew/common/d280x280.jpg"},{"title":"레이저, 키츠네 파이터 에디션 아쿠마 출시","contents":"<a name=\"category\" data-categoryno=\"8\" style=\"cursor: pointer\">취미/기타</a>","link":"https://www.funshop.co.kr/Story/FuntennaView/21328#","retrieved":1721952000000,"image":"https://cdn.funshop.co.kr/www/renew/common/d280x280.jpg"},{"title":"TeamGroup, PD20 미니 SSD 공개","contents":"<a name=\"category\" data-categoryno=\"2\" style=\"cursor: pointer\">PC/모바일</a>","link":"https://www.funshop.co.kr/Story/FuntennaView/21327#","retrieved":1721952000000,"image":"https://cdn.funshop.co.kr/abroad/042/21327/thumbnail_1.jpg"},{"title":"PDP, 철권 8 컬렉션 출시","contents":"<a name=\"category\" data-categoryno=\"8\" style=\"cursor: pointer\">취미/기타</a>","link":"https://www.funshop.co.kr/Story/FuntennaView/21326#","retrieved":1721865600000,"image":"https://cdn.funshop.co.kr/www/renew/common/d280x280.jpg"},{"title":"아야네오, 레트로 파워뱅크 출시","contents":"<a name=\"category\" data-categoryno=\"2\" style=\"cursor: pointer\">PC/모바일</a>","link":"https://www.funshop.co.kr/Story/FuntennaView/21325#","retrieved":1721865600000,"image":"https://cdn.funshop.co.kr/www/renew/common/d280x280.jpg"},{"title":"캐딜락, 2025 에스컬레이드 공개","contents":"<a name=\"category\" data-categoryno=\"1\" style=\"cursor: pointer\">자동차/모터사이클</a>","link":"https://www.funshop.co.kr/Story/FuntennaView/21324#","retrieved":1721865600000,"image":"https://cdn.funshop.co.kr/www/renew/common/d280x280.jpg"},{"title":"지샥, NASA 한정판 GW6900 출시","contents":"<a name=\"category\" data-categoryno=\"8\" style=\"cursor: pointer\">취미/기타</a>","link":"https://www.funshop.co.kr/Story/FuntennaView/21323#","retrieved":1721779200000,"image":"https://cdn.funshop.co.kr/www/renew/common/d280x280.jpg"},{"title":"Hyperkin, DuchesS Xbox 컨트롤러 출시","contents":"<a name=\"category\" data-categoryno=\"8\" style=\"cursor: pointer\">취미/기타</a>","link":"https://www.funshop.co.kr/Story/FuntennaView/21322#","retrieved":1721779200000,"image":"https://cdn.funshop.co.kr/www/renew/common/d280x280.jpg"}]}