{"title":"펀샵 ─ 펀테나 ─ 최신","url":"https://www.funshop.co.kr/Story/FuntennaList","favicon":"https://www.funshop.co.kr/Story/favicon.ico","elements":[{"title":"Creative, Zen Air True Wireless 이어폰 공개","contents":"<a name=\"category\" data-categoryno=\"8\" style=\"cursor: pointer\">취미/기타</a>","link":"https://www.funshop.co.kr/Story/FuntennaView/19933#","retrieved":1672790400000,"image":"https://cdn.funshop.co.kr/abroad/039/19933/thumbnail_1.jpg"},{"title":"Vans와 Timberland 최초의 협업 제품 출시","contents":"<a name=\"category\" data-categoryno=\"7\" style=\"cursor: pointer\">패션/시계/가방</a>","link":"https://www.funshop.co.kr/Story/FuntennaView/19932#","retrieved":1672790400000,"image":"https://cdn.funshop.co.kr/www/renew/common/d280x280.jpg"},{"title":"HYPERPACK PRO, 다양한 기능과 수납을 가진 모바일 툴킷 벡팩","contents":"<a name=\"category\" data-categoryno=\"7\" style=\"cursor: pointer\">패션/시계/가방</a>","link":"https://www.funshop.co.kr/Story/FuntennaView/19931#","retrieved":1672790400000,"image":"https://cdn.funshop.co.kr/abroad/039/19931/thumbnail_1.jpg"},{"title":"가방 같은 하드쉘 캐리어, Moln","contents":"<a name=\"category\" data-categoryno=\"7\" style=\"cursor: pointer\">패션/시계/가방</a>","link":"https://www.funshop.co.kr/Story/FuntennaView/19929#","retrieved":1672790400000,"image":"https://cdn.funshop.co.kr/abroad/039/19929/thumbnail_1.jpg"},{"title":"삼성, 43인치 게이밍 모니터 오디세이 네오 G7 출시","contents":"<a name=\"category\" data-categoryno=\"2\" style=\"cursor: pointer\">PC/모바일</a>","link":"https://www.funshop.co.kr/Story/FuntennaView/19927#","retrieved":1672704000000,"image":"https://cdn.funshop.co.kr/www/renew/common/d280x280.jpg"},{"title":"러기드 에어팟 케이스, GRAVITY Shock Resist Case Pro","contents":"<a name=\"category\" data-categoryno=\"8\" style=\"cursor: pointer\">취미/기타</a>","link":"https://www.funshop.co.kr/Story/FuntennaView/19926#","retrieved":1672704000000,"image":"https://cdn.funshop.co.kr/www/renew/common/d280x280.jpg"},{"title":"MSI, 하이엔드 게이밍 노트북 TITAN GT77 HX 13V 공개","contents":"<a name=\"category\" data-categoryno=\"2\" style=\"cursor: pointer\">PC/모바일</a>","link":"https://www.funshop.co.kr/Story/FuntennaView/19925#","retrieved":1672704000000,"image":"https://cdn.funshop.co.kr/www/renew/common/d280x280.jpg"},{"title":"RØDE NT-USB+, 프로페셔널 USB 마이크","contents":"<a name=\"category\" data-categoryno=\"8\" style=\"cursor: pointer\">취미/기타</a>","link":"https://www.funshop.co.kr/Story/FuntennaView/19928#","retrieved":1672617600000,"image":"https://cdn.funshop.co.kr/abroad/039/19928/thumbnail_1.jpg"}]}