{"title":"펀샵 ─ 펀테나 ─ 최신","url":"https://www.funshop.co.kr/Story/FuntennaList","favicon":"https://www.funshop.co.kr/Story/favicon.ico","elements":[{"title":"MOONDROP, 휴대용 CD 플레이어 DISCDREAM 공개.","contents":"<a name=\"category\" data-categoryno=\"8\" style=\"cursor: pointer\">취미/기타</a>","link":"https://www.funshop.co.kr/Story/FuntennaView/20929#","retrieved":1707177600000,"image":"https://cdn.funshop.co.kr/abroad/041/20929/thumbnail_1.jpg"},{"title":"에이수스, 웨어러블 디스플레이 에어비전 M1 공개","contents":"<a name=\"category\" data-categoryno=\"2\" style=\"cursor: pointer\">PC/모바일</a>","link":"https://www.funshop.co.kr/Story/FuntennaView/20928#","retrieved":1707177600000,"image":"https://cdn.funshop.co.kr/abroad/041/20928/thumbnail_1.jpg"},{"title":"필립스, 업무용 대형 커브드 모니터 출시","contents":"<a name=\"category\" data-categoryno=\"2\" style=\"cursor: pointer\">PC/모바일</a>","link":"https://www.funshop.co.kr/Story/FuntennaView/20927#","retrieved":1707177600000,"image":"https://cdn.funshop.co.kr/abroad/041/20927/thumbnail_1.jpg"},{"title":"Vapor Xbox 무선 컨트롤러 컬렉션 출시","contents":"<a name=\"category\" data-categoryno=\"8\" style=\"cursor: pointer\">취미/기타</a>","link":"https://www.funshop.co.kr/Story/FuntennaView/20926#","retrieved":1707091200000,"image":"https://cdn.funshop.co.kr/abroad/041/20926/thumbnail_1.jpg"},{"title":"나이키, 에어 맥스 Dn 출시 예정","contents":"<a name=\"category\" data-categoryno=\"7\" style=\"cursor: pointer\">패션/시계/가방</a>","link":"https://www.funshop.co.kr/Story/FuntennaView/20925#","retrieved":1707091200000,"image":"https://cdn.funshop.co.kr/abroad/041/20925/thumbnail_1.jpg"},{"title":"elgato, HDMI 2.1 캡처 카드 4K X 출시","contents":"<a name=\"category\" data-categoryno=\"2\" style=\"cursor: pointer\">PC/모바일</a>","link":"https://www.funshop.co.kr/Story/FuntennaView/20924#","retrieved":1707091200000,"image":"https://cdn.funshop.co.kr/abroad/041/20924/thumbnail_1.jpg"},{"title":"[해외펀딩] 듀얼 스크린 UMPC AYANEO FLIP DS","contents":"<a name=\"category\" data-categoryno=\"2\" style=\"cursor: pointer\">PC/모바일</a>","link":"https://www.funshop.co.kr/Story/FuntennaView/20923#","retrieved":1706832000000,"image":"https://cdn.funshop.co.kr/abroad/041/20923/thumbnail_1.jpg"},{"title":"스텔라 블레이드, PS5로 출시 곧 출시예정","contents":"<a name=\"category\" data-categoryno=\"8\" style=\"cursor: pointer\">취미/기타</a>","link":"https://www.funshop.co.kr/Story/FuntennaView/20922#","retrieved":1706832000000,"image":"https://cdn.funshop.co.kr/abroad/041/20922/thumbnail_1.jpg"}]}