{"title":"펀샵 ─ 펀테나 ─ 최신","url":"https://www.funshop.co.kr/Story/FuntennaList","favicon":"https://www.funshop.co.kr/Story/favicon.ico","elements":[{"title":"닌텐도, 끝내주게 춤춰라 메이드 인 와리오 공개","contents":"<a name=\"category\" data-categoryno=\"8\" style=\"cursor: pointer\">취미/기타</a>","link":"https://www.funshop.co.kr/Story/FuntennaView/20376#","retrieved":1687737600000,"image":"https://cdn.funshop.co.kr/abroad/040/20376/thumbnail_1.jpg"},{"title":"BEYERDYNAMIC, 스페이스 맥스 스피커폰 출시","contents":"<a name=\"category\" data-categoryno=\"8\" style=\"cursor: pointer\">취미/기타</a>","link":"https://www.funshop.co.kr/Story/FuntennaView/20375#","retrieved":1687737600000,"image":"https://cdn.funshop.co.kr/abroad/040/20375/thumbnail_1.jpg"},{"title":"RICOH, 휴대용 모니터 150/150BW 출시","contents":"<a name=\"category\" data-categoryno=\"2\" style=\"cursor: pointer\">PC/모바일</a>","link":"https://www.funshop.co.kr/Story/FuntennaView/20374#","retrieved":1687737600000,"image":"https://cdn.funshop.co.kr/abroad/040/20374/thumbnail_1.jpg"},{"title":"[해외펀딩] 세기말 감성의 무선 충전 보조 배터리 Wizman Green Powerbank.","contents":"<a name=\"category\" data-categoryno=\"2\" style=\"cursor: pointer\">PC/모바일</a>","link":"https://www.funshop.co.kr/Story/FuntennaView/20372#","retrieved":1687478400000,"image":"https://cdn.funshop.co.kr/abroad/040/20372/thumbnail_1.jpg"},{"title":"bauhutte의 게이밍 소파 디럭스","contents":"<a name=\"category\" data-categoryno=\"8\" style=\"cursor: pointer\">취미/기타</a>","link":"https://www.funshop.co.kr/Story/FuntennaView/20371#","retrieved":1687478400000,"image":"https://cdn.funshop.co.kr/abroad/040/20371/thumbnail_1.jpg"},{"title":"반스 X 타카 하야시, 발목가드 Era 공개","contents":"<a name=\"category\" data-categoryno=\"7\" style=\"cursor: pointer\">패션/시계/가방</a>","link":"https://www.funshop.co.kr/Story/FuntennaView/20370#","retrieved":1687478400000,"image":"https://cdn.funshop.co.kr/abroad/040/20370/thumbnail_1.jpg"},{"title":"슈퍼마리오 RPG 리메이크 공개","contents":"<a name=\"category\" data-categoryno=\"8\" style=\"cursor: pointer\">취미/기타</a>","link":"https://www.funshop.co.kr/Story/FuntennaView/20368#","retrieved":1687478400000,"image":"https://cdn.funshop.co.kr/abroad/040/20368/thumbnail_1.jpg"},{"title":"[해외펀딩] 심비오트 스피커 Van der Waals.","contents":"<a name=\"category\" data-categoryno=\"2\" style=\"cursor: pointer\">PC/모바일</a>","link":"https://www.funshop.co.kr/Story/FuntennaView/20369#","retrieved":1687392000000,"image":"https://cdn.funshop.co.kr/abroad/040/20369/thumbnail_1.jpg"}]}